artifact/__init__.py
configuration/__init__.py
model_manager/__init__.py
nfx-0.0.0.dist-info/METADATA
nfx-0.0.0.dist-info/WHEEL
nfx-0.0.0.dist-info/top_level.txt
nfx-0.0.0.dist-info/RECORD
