Metadata-Version: 2.1
Name: nfx
Version: 0.0.0
Summary: Neuro Flow Extended
Author: Avnish Yadav
